sopel_lichess/__init__.py
sopel_lichess/config.py
sopel_lichess/parsers.py
sopel_lichess/plugin.py
sopel_lichess-0.2.1.dist-info/LICENSE.txt
sopel_lichess-0.2.1.dist-info/METADATA
sopel_lichess-0.2.1.dist-info/WHEEL
sopel_lichess-0.2.1.dist-info/entry_points.txt
sopel_lichess-0.2.1.dist-info/top_level.txt
sopel_lichess-0.2.1.dist-info/RECORD
