Metadata-Version: 2.1
Name: sopel-lichess
Version: 0.2.1
Summary: Lichess plugin for Sopel
Home-page: https://github.com/Exirel/sopel-lichess
Author: Florian Strzelecki
Author-email: florian.strzelecki@gmail.com
License: Eiffel Forum License, version 2
Keywords: sopel plugin lichess chess bot irc
Platform: Linux x86
Platform: x86-64
Classifier: Development Status :: 4 - Beta
Classifier: Intended Audience :: Developers
Classifier: Intended Audience :: System Administrators
Classifier: License :: Eiffel Forum License (EFL)
Classifier: License :: OSI Approved :: Eiffel Forum License
Classifier: Operating System :: POSIX :: Linux
Classifier: Programming Language :: Python :: 3.6
Classifier: Programming Language :: Python :: 3.7
Classifier: Programming Language :: Python :: 3.8
Classifier: Programming Language :: Python :: 3.9
Classifier: Topic :: Communications :: Chat :: Internet Relay Chat
Requires-Python: <4,>=3.6
License-File: LICENSE.txt
Requires-Dist: requests
Requires-Dist: sopel (>=7.1)
